{
  "title": "O Nosso Menu",
  "subtitle": "Ingredientes frescos, preparados diariamente com carinho",
  "chefs_pick": "Escolha do Chef",
  "categories": [
    {
      "key": "starters",
      "label": "Entradas",
      "items": [
        { "name": "Bruschetta", "description": "Pão de fermentação natural com tomate, manjericão e azeite", "price": "9€", "image": "" },
        { "name": "Sopa do Dia", "description": "Pergunte ao seu servidor pela seleção sazonal de hoje", "price": "8€", "image": "" },
        { "name": "Tábua de Frios", "description": "Enchidos curados, queijos artesanais e pickles caseiros", "price": "18€", "image": "" },
        { "name": "Calamares Fritos", "description": "Ligeiramente empanados com aioli de limão", "price": "14€", "image": "" }
      ]
    },
    {
      "key": "mains",
      "label": "Principais",
      "items": [
        { "name": "Salmão Grelhado", "description": "Com legumes da época e manteiga de limão e alcaparras", "price": "26€", "image": "" },
        { "name": "Lombo de Vaca", "description": "225g com puré de trufa e molho de vinho tinto", "price": "34€", "image": "" },
        { "name": "Risotto de Cogumelos", "description": "Arroz arbório com cogumelos silvestres e parmesão", "price": "22€", "image": "" },
        { "name": "Frango Assado", "description": "Meio frango com manteiga de ervas e batatas assadas", "price": "24€", "image": "" }
      ]
    },
    {
      "key": "desserts",
      "label": "Sobremesas",
      "items": [
        { "name": "Tiramisu", "description": "Clássica sobremesa italiana com espresso e mascarpone", "price": "10€", "image": "" },
        { "name": "Bolo de Chocolate", "description": "Quente com chocolate negro e gelado de baunilha", "price": "11€", "image": "" },
        { "name": "Panna Cotta", "description": "Creme de baunilha com compota de frutos vermelhos", "price": "9€", "image": "" }
      ]
    },
    {
      "key": "drinks",
      "label": "Bebidas",
      "items": [
        { "name": "Vinho da Casa", "description": "Tinto ou branco — pergunte pela seleção de hoje, copo", "price": "8€", "image": "" },
        { "name": "Cerveja Artesanal", "description": "Torneira rotativa local, imperial", "price": "7€", "image": "" },
        { "name": "Limonada Natural", "description": "Espremida na hora com hortelã", "price": "5€", "image": "" },
        { "name": "Café Especial", "description": "Espresso, cappuccino ou flat white", "price": "5€", "image": "" }
      ]
    }
  ]
}
